predigame/Actor.py
predigame/Animation.py
predigame/GameAI.py
predigame/Globals.py
predigame/Inventory.py
predigame/Level.py
predigame/Maze.py
predigame/Sprite.py
predigame/Statistics.py
predigame/Thing.py
predigame/__init__.py
predigame/api.py
predigame/constants.py
predigame/globs.py
predigame/predigame.py
predigame/utils.py
predigame/images/error.png
predigame/images/screenshot.png
predigame-1.2.0.dist-info/DESCRIPTION.rst
predigame-1.2.0.dist-info/METADATA
predigame-1.2.0.dist-info/RECORD
predigame-1.2.0.dist-info/WHEEL
predigame-1.2.0.dist-info/entry_points.txt
predigame-1.2.0.dist-info/metadata.json
predigame-1.2.0.dist-info/top_level.txt
