Metadata-Version: 2.0
Name: predigame
Version: 1.2.0
Summary: An instructional game development platform
Home-page: http://predigame.io
Author: Predicate Academy
Author-email: support@predigame.io
License: UNKNOWN
Platform: UNKNOWN
Requires-Dist: pygame
Requires-Dist: pillow
Requires-Dist: astar (==0.9)
Requires-Dist: PyGithub (==1.38)
